cli_code/__init__.py
cli_code/config.py
cli_code/main.py
cli_code/utils.py
cli_code/models/__init__.py
cli_code/models/base.py
cli_code/models/constants.py
cli_code/models/gemini.py
cli_code/models/ollama.py
cli_code/tools/__init__.py
cli_code/tools/base.py
cli_code/tools/directory_tools.py
cli_code/tools/file_tools.py
cli_code/tools/quality_tools.py
cli_code/tools/summarizer_tool.py
cli_code/tools/system_tools.py
cli_code/tools/task_complete_tool.py
cli_code/tools/test_runner.py
cli_code/tools/tree_tool.py
cli_code_agent-0.3.0.dist-info/METADATA
cli_code_agent-0.3.0.dist-info/WHEEL
cli_code_agent-0.3.0.dist-info/entry_points.txt
cli_code_agent-0.3.0.dist-info/top_level.txt
cli_code_agent-0.3.0.dist-info/RECORD
