Metadata-Version: 2.4
Name: cli-code-agent
Version: 0.3.0
Summary: An AI coding assistant CLI using Google's Gemini models with function calling.
Author-email: James Nguyen <git@nocentre.net>
License-Expression: MIT
Project-URL: Homepage, https://github.com/BlueCentre/cli-code
Project-URL: Bug Tracker, https://github.com/BlueCentre/cli-code/issues
Classifier: Programming Language :: Python :: 3
Classifier: Operating System :: OS Independent
Classifier: Development Status :: 3 - Alpha
Classifier: Environment :: Console
Classifier: Intended Audience :: Developers
Classifier: Topic :: Software Development
Classifier: Topic :: Utilities
Requires-Python: >=3.9
Requires-Dist: google-generativeai>=0.5.0
Requires-Dist: click>=8.0
Requires-Dist: rich>=13.0
Requires-Dist: PyYAML>=6.0
Requires-Dist: tiktoken>=0.6.0
Requires-Dist: questionary>=2.0.0
Requires-Dist: openai>=1.0.0
Requires-Dist: protobuf>=4.0.0
Requires-Dist: google-cloud-aiplatform
Provides-Extra: dev
Requires-Dist: build>=1.0.0; extra == "dev"
Requires-Dist: pytest>=7.0.0; extra == "dev"
Requires-Dist: pytest-timeout>=2.2.0; extra == "dev"
Requires-Dist: pytest-mock>=3.6.0; extra == "dev"
Requires-Dist: ruff>=0.1.0; extra == "dev"
Requires-Dist: protobuf>=4.0.0; extra == "dev"
